co2mini/__init__.py
co2mini/config.py
co2mini/homekit.py
co2mini/main.py
co2mini/meter.py
co2mini/mqtt.py
co2mini-0.4.0.dist-info/LICENSE
co2mini-0.4.0.dist-info/METADATA
co2mini-0.4.0.dist-info/WHEEL
co2mini-0.4.0.dist-info/entry_points.txt
co2mini-0.4.0.dist-info/top_level.txt
co2mini-0.4.0.dist-info/RECORD
