Metadata-Version: 2.1
Name: co2mini
Version: 0.4.0
Summary: Monitor CO2 levels with Prometheus and/or HomeKit
Author: Jeremy Mayeres
Author-email: jeremy@jerr.dev
License: MIT License
Project-URL: repository, https://github.com/jerr0328/co2-mini
Keywords: co2,co2mini,temperature,humidity,sensors,prometheus,homekit
Classifier: Programming Language :: Python :: 3
Classifier: License :: OSI Approved :: MIT License
Classifier: Operating System :: OS Independent
Classifier: Development Status :: 3 - Alpha
Requires-Python: >=3.9
License-File: LICENSE
Requires-Dist: prometheus-client
Requires-Dist: environs
Provides-Extra: all
Requires-Dist: co2mini[homekit,mqtt] ; extra == 'all'
Provides-Extra: homekit
Requires-Dist: hap-python ; extra == 'homekit'
Provides-Extra: mqtt
Requires-Dist: paho-mqtt ; extra == 'mqtt'
